LICENSE
MANIFEST.in
README.md
setup.py
examples/__init__.py
examples/darcy.py
examples/elastic.py
examples/elastic_model.py
examples/elastic_model_multi_step.py
examples/freecad_simple_geometry.py
examples/heat.py
examples/pygmsh_simple_geometry.py
fempy/__init__.py
fempy/compat.py
fempy/testing.py
fempy.egg-info/PKG-INFO
fempy.egg-info/SOURCES.txt
fempy.egg-info/dependency_links.txt
fempy.egg-info/requires.txt
fempy.egg-info/top_level.txt
fempy/domain/__init__.py
fempy/domain/domain.py
fempy/domain/elems.py
fempy/domain/index.py
fempy/domain/tools.py
fempy/fields/__init__.py
fempy/fields/algebra.py
fempy/fields/fields.py
fempy/fields/gfields.py
fempy/fields/nfields.py
fempy/fields/operators.py
fempy/fields/tools.py
fempy/geometry/__init__.py
fempy/geometry/geometry.py
fempy/geometry/gmsh.py
fempy/geometry/gmsh_io.py
fempy/geometry/shapes.py
fempy/geometry/tools.py
fempy/models/__init__.py
fempy/models/elastic.py
fempy/models/heat.py
fempy/models/heatandmoisture.py
fempy/models/model.py
fempy/solvers/__init__.py
fempy/solvers/_bdf.py
fempy/solvers/_solver.py
fempy/solvers/ivp.py
fempy/solvers/linear.py
fempy/solvers/methods.py
fempy/solvers/nonlin.py
fempy/solvers/precon.py
fempy/solvers/tools.py
tests/__init__.py
tests/common.py
tests/runtests.py
tests/data/circle3n.conec
tests/data/circle3n.coors
tests/data/circle6n.conec
tests/data/circle6n.coors
tests/data/circum2n.conec
tests/data/circum2n.coors
tests/data/circum3n.conec
tests/data/circum3n.coors
tests/data/cylinder10n.conec
tests/data/cylinder10n.coors
tests/data/cylinder4n.conec
tests/data/cylinder4n.coors
tests/data/line2n.conec
tests/data/line2n.coors
tests/data/line3n.conec
tests/data/line3n.coors
tests/data/mscipy.sol
tests/data/paraboloid3n.conec
tests/data/paraboloid3n.coors
tests/data/paraboloid6n.conec
tests/data/paraboloid6n.coors
tests/data/simple3D.conec0D
tests/data/simple3D.conec1D
tests/data/simple3D.conec2D
tests/data/simple3D.conec3D
tests/data/simple3D.coors
tests/data/spiral2n.conec
tests/data/spiral2n.coors
tests/data/spiral3n.conec
tests/data/spiral3n.coors
tests/data/elastic/mesh1.axisym.sol
tests/data/elastic/mesh1.conec
