Metadata-Version: 2.1
Name: fempy
Version: 0.3.1
Summary: Finite element method in python
Home-page: http://fempy.org
Author: Marek Wojciechowski
Author-email: mwojc@p.lodz.pl
License: LGPL-3
Keywords: FEM, fem, finite element method
Platform: Posix
Platform: Windows
Classifier: Development Status :: 4 - Beta
Classifier: Intended Audience :: Education
Classifier: Intended Audience :: Science/Research
Classifier: License :: OSI Approved :: GNU General Public License v2 or later (GPLv2+)
Classifier: Operating System :: POSIX :: Linux
Classifier: Operating System :: Microsoft :: Windows
Classifier: Operating System :: MacOS :: MacOS X
Classifier: Programming Language :: C
Classifier: Programming Language :: C++
Classifier: Programming Language :: Python :: Implementation :: CPython
Classifier: Topic :: Scientific/Engineering
